PyFuzzySet/Cluster.py
PyFuzzySet/ClusterValidity.py
PyFuzzySet/__init__.py
pyfuzzyset-0.0.12.dist-info/LICENCE.txt
pyfuzzyset-0.0.12.dist-info/METADATA
pyfuzzyset-0.0.12.dist-info/WHEEL
pyfuzzyset-0.0.12.dist-info/top_level.txt
pyfuzzyset-0.0.12.dist-info/RECORD
