Metadata-Version: 2.1
Name: pyfuzzyset
Version: 0.0.12
Summary: Includes Fuzzy Set Algorithms, Intuitionistic Fuzzy Set Algorithms and Fuzzy Cluster Validity Indexes
Home-page: https://github.com/ibrahimayaz/pyfuzzyset
Author: İbrahim AYAZ, Fatih KUTLU
Author-email: ayazibrahim13@gmail.com
License: MIT
Keywords: fuzzy set clustering intuitionistic sezgisel bulanık küme
Platform: UNKNOWN
Classifier: Development Status :: 5 - Production/Stable
Classifier: Intended Audience :: Education
Classifier: Operating System :: OS Independent
Classifier: License :: OSI Approved :: MIT License
Classifier: Programming Language :: Python :: 2.7
Classifier: Programming Language :: Python :: 3
Classifier: Programming Language :: Python :: 3.7
Classifier: Programming Language :: Python :: 3.8
Classifier: Programming Language :: Python :: 3.9
